dax_extract/__init__.py
scripts/__init__.py
scripts/daxextract.py
PyDaxExtract-0.2.1.dist-info/LICENSE.txt
PyDaxExtract-0.2.1.dist-info/METADATA
PyDaxExtract-0.2.1.dist-info/WHEEL
PyDaxExtract-0.2.1.dist-info/entry_points.txt
PyDaxExtract-0.2.1.dist-info/top_level.txt
PyDaxExtract-0.2.1.dist-info/zip-safe
PyDaxExtract-0.2.1.dist-info/RECORD
