Metadata-Version: 2.1
Name: PyDaxExtract
Version: 0.2.1
Summary: Extract Table Relationships, m expressions, and DAX expressions from Power BI template.
Home-page: https://gitlab.com/doug.shawhan/pydaxextract
Author: Doug Shawhan
Author-email: doug.shawhan@gmail.com
License: Copyright 2021 Doug Shawhan        
Project-URL: Bug Tracker, https://gitlab.com/doug.shawhan/pydaxextract/issues
Project-URL: Source Code, https://gitlab.com/doug.shawhan/pydaxextract/tree/dev
Project-URL: Documentation, https://pydaxextract.readthedocs.io
Platform: any
Classifier: Development Status :: 4 - Beta
Classifier: Intended Audience :: Developers
Classifier: License :: OSI Approved :: BSD License
Classifier: Operating System :: OS Independent
Classifier: Programming Language :: Python
Classifier: Programming Language :: Python :: 3.7
Classifier: Programming Language :: Python :: 3.8
Classifier: Programming Language :: Python :: 3.9
License-File: LICENSE.txt
